rexeloft_llc/__init__.py
rexeloft_llc/intelix/__init__.py
rexeloft_llc/intelix/chatbot.py
rexeloft_llc-1.1.dist-info/LICENSE
rexeloft_llc-1.1.dist-info/METADATA
rexeloft_llc-1.1.dist-info/WHEEL
rexeloft_llc-1.1.dist-info/entry_points.txt
rexeloft_llc-1.1.dist-info/top_level.txt
rexeloft_llc-1.1.dist-info/RECORD
