Metadata-Version: 2.1
Name: rexeloft_llc
Version: 1.1
Summary: A free chatbot (intelix) Python library made by Rexeloft LLC [Beta]
Home-page: https://github.com/OfficialDex
Author: Rexeloft LLC
License: MIT
Keywords: chatbot,chat,Ai,smart,bot,new,Artifical intelligence,intelix,rexeloft,intelligence
Classifier: Programming Language :: Python :: 3
Classifier: License :: OSI Approved :: MIT License
Classifier: Operating System :: OS Independent
Requires-Python: >=3.6
License-File: LICENSE
Requires-Dist: nltk
Requires-Dist: googletrans==4.0.0rc1
Requires-Dist: fuzzywuzzy
Requires-Dist: requests
Requires-Dist: vaderSentiment
Requires-Dist: python-Levenshtein
